Metadata-Version: 1.1
Name: pyqpecgen
Version: 0.1.0
Summary: A QPEC problem generator for Python
Home-page: https://github.com/discardthree/PyQPECgen
Author: Trish Gillett-Kawamoto
Author-email: discardthree@gmail.com
License: MIT
Platform: UNKNOWN
Classifier: Development Status :: 3 - Alpha
Classifier: License :: OSI Approved :: MIT License
Classifier: Natural Language :: English
Classifier: Programming Language :: Python
Classifier: Intended Audience :: Science/Research
Classifier: Topic :: Scientific/Engineering :: Mathematics
